falcon_auth2/__init__.py
falcon_auth2/exc.py
falcon_auth2/getter.py
falcon_auth2/middleware.py
falcon_auth2/backends/__init__.py
falcon_auth2/backends/base.py
falcon_auth2/backends/basic.py
falcon_auth2/backends/jwt.py
falcon_auth2/backends/meta.py
falcon_auth2/utils/__init__.py
falcon_auth2/utils/asyncio_compat.py
falcon_auth2/utils/classes.py
falcon_auth2/utils/compat.py
falcon_auth2/utils/functions.py
falcon_auth2-0.1.0.dist-info/LICENSE
falcon_auth2-0.1.0.dist-info/METADATA
falcon_auth2-0.1.0.dist-info/WHEEL
falcon_auth2-0.1.0.dist-info/top_level.txt
falcon_auth2-0.1.0.dist-info/RECORD
