Metadata-Version: 2.1
Name: falcon-auth2
Version: 0.1.0
Summary: Falcon authentication middleware that supports multiple authentication types.
Home-page: https://github.com/CaselIT/falcon-auth2
Author: Federico Caselli
Author-email: cfederico87+pypi@gmail.com
License: Apache-2.0,
Project-URL: Documentation, https://falcon-auth2.readthedocs.io
Project-URL: Issue Tracker, https://github.com/CaselIT/falcon-auth2/issues
Keywords: falcon,web,api,middleware,auth,authentication
Platform: UNKNOWN
Classifier: Development Status :: 3 - Alpha
Classifier: Environment :: Web Environment
Classifier: Intended Audience :: Developers
Classifier: License :: OSI Approved :: Apache Software License
Classifier: Operating System :: OS Independent
Classifier: Programming Language :: Python
Classifier: Programming Language :: Python :: 3
Classifier: Programming Language :: Python :: 3.6
Classifier: Programming Language :: Python :: 3.7
Classifier: Programming Language :: Python :: 3.8
Classifier: Programming Language :: Python :: 3.9
Classifier: Programming Language :: Python :: 3.10
Classifier: Programming Language :: Python :: Implementation :: CPython
Classifier: Programming Language :: Python :: Implementation :: PyPy
Classifier: Topic :: Internet :: WWW/HTTP :: WSGI :: Middleware
Classifier: Topic :: Software Development :: Libraries :: Python Modules
Requires-Python: >=3.6
License-File: LICENSE
Requires-Dist: falcon (>=2)
Provides-Extra: async
Requires-Dist: greenlet (!=0.4.17) ; extra == 'async'
Provides-Extra: jwt
Requires-Dist: authlib (>=0.15.5) ; extra == 'jwt'
